{
  "version": 1,
  "generated": "2026-06-26T19:27:01.218946+00:00",
  "voice": "zh-CN-XiaoxiaoNeural",
  "chapters": [
    {
      "title": "《毛选》精读 · 矛盾论：主要矛盾与对立统一",
      "start": 0.0,
      "end": 15.408
    },
    {
      "title": "写作背景",
      "start": 15.408,
      "end": 52.032
    },
    {
      "title": "原文摘录",
      "start": 52.032,
      "end": 106.128
    },
    {
      "title": "逐段精解",
      "start": 106.128,
      "end": 344.688
    },
    {
      "title": "思想坐标",
      "start": 344.688,
      "end": 383.592
    },
    {
      "title": "当代映射：给做事者的启发",
      "start": 383.592,
      "end": 434.904
    },
    {
      "title": "个人体悟",
      "start": 434.904,
      "end": 478.56
    }
  ]
}